alkivi/__init__.py
alkivi/config/__init__.py
alkivi/config/manager.py
alkivi_config_manager-1.2.9.dist-info/METADATA
alkivi_config_manager-1.2.9.dist-info/RECORD
alkivi_config_manager-1.2.9.dist-info/WHEEL
alkivi_config_manager-1.2.9.dist-info/top_level.txt
