Metadata-Version: 2.1
Name: alkivi-config-manager
Version: 1.2.9
Summary: Python config-manager used at Alkivi
Home-page: https://github.com/alkivi-sas/python-alkivi-config-manager
Author: Anthony Martinet
Author-email: anthony@alkivi.fr
License: LGPLv3
Keywords: alkivi config configuration manager
Platform: UNKNOWN
Classifier: Development Status :: 4 - Beta
Classifier: Environment :: Console
Classifier: Intended Audience :: Developers
Classifier: Topic :: Software Development :: Build Tools
Classifier: License :: OSI Approved :: GNU Lesser General Public License v3 (LGPLv3)
Classifier: Programming Language :: Python :: 2
Classifier: Programming Language :: Python :: 2.7
Classifier: Programming Language :: Python :: 3
Classifier: Programming Language :: Python :: 3.2
Classifier: Programming Language :: Python :: 3.3
Classifier: Programming Language :: Python :: 3.4
Classifier: Programming Language :: Python :: 3.5
Provides-Extra: test
Provides-Extra: dev
Provides-Extra: dev
Provides-Extra: test
